{
  "updated_at": "2026-05-24T01:30:01+08:00",
  "scraped_date": "2026-05-24",
  "prev_date": "2026-05-23",
  "summary": {
    "total_active": 60,
    "total_vacant": 8,
    "total_expired": 7,
    "total_expiring": 0,
    "featured_count": 0,
    "super_top_count": 41,
    "normal_top_count": 0,
    "owner_count": 17
  },
  "packages": [
    {
      "num": 1,
      "active": 17,
      "vacant": 8,
      "unlisted": 0,
      "expired": 0
    },
    {
      "num": 2,
      "active": 25,
      "vacant": 0,
      "unlisted": 0,
      "expired": 0
    },
    {
      "num": 3,
      "active": 18,
      "vacant": 0,
      "unlisted": 0,
      "expired": 7
    }
  ],
  "items": [
    {
      "link_id": "21138327",
      "title": "【優式】南勢角站/靜巷內庭院透天3房/可養寵物",
      "href": "https://rent.591.com.tw/21138327",
      "package_num": 3,
      "days": 4,
      "status": "active",
      "owner": "關宗宇",
      "featured": false,
      "topped": "超級置頂"
    },
    {
      "link_id": "21138369",
      "title": "【優式】大安站/都會樹海景觀房/設計師家具、拎包入住",
      "href": "https://rent.591.com.tw/21138369",
      "package_num": 3,
      "days": 4,
      "status": "active",
      "owner": "關宗宇",
      "featured": false,
      "topped": ""
    },
    {
      "link_id": "21299354",
      "title": "徐匯中學/屋齡輕採光大2房/生活機能佳🌟馬丁",
      "href": "https://rent.591.com.tw/21299354",
      "package_num": 3,
      "days": 4,
      "status": "active",
      "owner": "關宗宇",
      "featured": false,
      "topped": "超級置頂"
    },
    {
      "link_id": "21151001",
      "title": "🌿西門商圈｜電梯2房｜生活機能佳｜大台北生活圈｜小方🌿",
      "href": "https://rent.591.com.tw/21151001",
      "package_num": 3,
      "days": 5,
      "status": "active",
      "owner": "方鼎文",
      "featured": false,
      "topped": "超級置頂"
    },
    {
      "link_id": "21297242",
      "title": "C台北橋站丨含網路第四台丨獨立衛浴丨共用陽台",
      "href": "https://rent.591.com.tw/21297242",
      "package_num": 3,
      "days": 7,
      "status": "active",
      "owner": "蕭靜芳",
      "featured": false,
      "topped": "超級置頂"
    },
    {
      "link_id": "21285572",
      "title": "大安站丨質感整層景觀宅丨拎包入住",
      "href": "https://rent.591.com.tw/21285572",
      "package_num": 3,
      "days": 8,
      "status": "active",
      "owner": "劉子碩",
      "featured": false,
      "topped": ""
    },
    {
      "link_id": "21296181",
      "title": "徐匯中學丨電梯丨邊間採光佳丨屋況乾淨🌟Wei🌟",
      "href": "https://rent.591.com.tw/21296181",
      "package_num": 3,
      "days": 8,
      "status": "active",
      "owner": "張忠豪",
      "featured": false,
      "topped": ""
    },
    {
      "link_id": "21302979",
      "title": "徐匯中學丨電梯可租補丨租金含水丨質感裝潢🌟忠豪🌟",
      "href": "https://rent.591.com.tw/21302979",
      "package_num": 3,
      "days": 8,
      "status": "active",
      "owner": "張忠豪",
      "featured": false,
      "topped": ""
    },
    {
      "link_id": "21292440",
      "title": "徐匯中學站｜高樓景觀2房｜空間舒適｜寵可談🌺Amber🌺",
      "href": "https://rent.591.com.tw/21292440",
      "package_num": 3,
      "days": 9,
      "status": "active",
      "owner": "林佳燕",
      "featured": false,
      "topped": "超級置頂"
    },
    {
      "link_id": "21209511",
      "title": "⭐景安站⭐捷運共構宅｜大空間好規劃｜包裹垃圾代收🌈卓威🌈",
      "href": "https://rent.591.com.tw/21209511",
      "package_num": 3,
      "days": 11,
      "status": "active",
      "owner": "未知",
      "featured": false,
      "topped": "超級置頂"
    },
    {
      "link_id": "21195203",
      "title": "菜寮丨可租補報稅丨可貓丨採光佳丨系統收納🌟忠豪🌟",
      "href": "https://rent.591.com.tw/21195203",
      "package_num": 3,
      "days": 12,
      "status": "active",
      "owner": "張忠豪",
      "featured": false,
      "topped": "超級置頂"
    },
    {
      "link_id": "21195341",
      "title": "三民高中丨專屬露台丨雙衛浴丨可另租車位⭐️忠豪⭐️",
      "href": "https://rent.591.com.tw/21195341",
      "package_num": 3,
      "days": 12,
      "status": "active",
      "owner": "張忠豪",
      "featured": false,
      "topped": "超級置頂"
    },
    {
      "link_id": "21238677",
      "title": "三和國中丨可租補報稅丨房間乾淨丨生活機能佳🌟忠豪🌟",
      "href": "https://rent.591.com.tw/21238677",
      "package_num": 3,
      "days": 12,
      "status": "active",
      "owner": "張忠豪",
      "featured": false,
      "topped": "超級置頂"
    },
    {
      "link_id": "21270218",
      "title": "🎉萬華｜可租補報稅｜質感設計採光｜全新未入住🍀阿宣🍀",
      "href": "https://rent.591.com.tw/21270218",
      "package_num": 3,
      "days": 12,
      "status": "active",
      "owner": "未知",
      "featured": false,
      "topped": ""
    },
    {
      "link_id": "21196871",
      "title": "🎉菜寮站｜質感設計｜採光三房｜可租補可貓平面車位🍀阿宣",
      "href": "https://rent.591.com.tw/21196871",
      "package_num": 3,
      "days": 12,
      "status": "active",
      "owner": "林宣佑",
      "featured": false,
      "topped": ""
    },
    {
      "link_id": "21253721",
      "title": "菜寮丨可租補報稅丨可貓丨系統收納丨採光佳🌟Wei🌟",
      "href": "https://rent.591.com.tw/21253721",
      "package_num": 3,
      "days": 12,
      "status": "active",
      "owner": "蕭眞儀",
      "featured": false,
      "topped": ""
    },
    {
      "link_id": "18909014",
      "title": "🌈三和國中站｜新裝潢｜新家具｜北歐風設計☀️阿傳☀️",
      "href": "https://rent.591.com.tw/18909014",
      "package_num": 3,
      "days": 12,
      "status": "active",
      "owner": "詹張傳",
      "featured": false,
      "topped": ""
    },
    {
      "link_id": "21299428",
      "title": "【優式】象山站/飯店式管理住宅/拎包入住",
      "href": "https://rent.591.com.tw/21299428",
      "package_num": 3,
      "days": 12,
      "status": "active",
      "owner": "關宗宇",
      "featured": false,
      "topped": ""
    },
    {
      "link_id": "21206400",
      "title": "【優式】忠孝復興站，家具齊全、可租補",
      "href": "https://rent.591.com.tw/21206400",
      "package_num": 2,
      "days": 14,
      "status": "active",
      "owner": "未知",
      "featured": false,
      "topped": "超級置頂"
    },
    {
      "link_id": "21211568",
      "title": "徐匯中學站/高樓採光景觀2房/生活機能佳⭐馬丁",
      "href": "https://rent.591.com.tw/21211568",
      "package_num": 2,
      "days": 14,
      "status": "active",
      "owner": "未知",
      "featured": false,
      "topped": "超級置頂"
    },
    {
      "link_id": "21253941",
      "title": "⭐️板橋站丨可租補報稅丨含管丨可租平面車位",
      "href": "https://rent.591.com.tw/21253941",
      "package_num": 2,
      "days": 14,
      "status": "active",
      "owner": "蕭靜芳",
      "featured": false,
      "topped": "超級置頂"
    },
    {
      "link_id": "21297466",
      "title": "⭐️H三和國中站丨女性丨有陽台洗衣機可使用",
      "href": "https://rent.591.com.tw/21297466",
      "package_num": 2,
      "days": 14,
      "status": "active",
      "owner": "蕭靜芳",
      "featured": false,
      "topped": "超級置頂"
    },
    {
      "link_id": "21221010",
      "title": "🎉板橋站｜可租補報稅｜質感系統設計｜景觀2房🍀阿宣🍀",
      "href": "https://rent.591.com.tw/21221010",
      "package_num": 2,
      "days": 15,
      "status": "active",
      "owner": "林宣佑",
      "featured": false,
      "topped": "超級置頂"
    },
    {
      "link_id": "21272695",
      "title": "三民高中丨可租補丨低樓層丨租金含水丨屋況乾淨🌟忠豪🌟",
      "href": "https://rent.591.com.tw/21272695",
      "package_num": 2,
      "days": 16,
      "status": "active",
      "owner": "張忠豪",
      "featured": false,
      "topped": "超級置頂"
    },
    {
      "link_id": "21224108",
      "title": "🎉西門站｜飯店管理｜乾淨舒適｜系統收納🍀阿宣",
      "href": "https://rent.591.com.tw/21224108",
      "package_num": 2,
      "days": 16,
      "status": "active",
      "owner": "未知",
      "featured": false,
      "topped": "超級置頂"
    },
    {
      "link_id": "21264717",
      "title": "三民高中站丨採光明亮大3房丨貓可議⭐️馬丁",
      "href": "https://rent.591.com.tw/21264717",
      "package_num": 2,
      "days": 16,
      "status": "active",
      "owner": "關宗宇",
      "featured": false,
      "topped": ""
    },
    {
      "link_id": "21229539",
      "title": "南勢角站/靜巷內一樓大三房/生活機能佳",
      "href": "https://rent.591.com.tw/21229539",
      "package_num": 2,
      "days": 17,
      "status": "active",
      "owner": "關宗宇",
      "featured": false,
      "topped": "超級置頂"
    },
    {
      "link_id": "21295467",
      "title": "板橋區｜質感電梯二房｜採光佳｜小謙",
      "href": "https://rent.591.com.tw/21295467",
      "package_num": 2,
      "days": 18,
      "status": "active",
      "owner": "曾宇謙",
      "featured": false,
      "topped": ""
    },
    {
      "link_id": "21279644",
      "title": "🎉板橋區｜質感電梯二房｜採光佳｜拎包入住🍀阿宣🍀",
      "href": "https://rent.591.com.tw/21279644",
      "package_num": 2,
      "days": 18,
      "status": "active",
      "owner": "未知",
      "featured": false,
      "topped": "超級置頂"
    },
    {
      "link_id": "21293629",
      "title": "徐匯中學站｜電梯2房｜採光通風佳🍀阿宣🍀",
      "href": "https://rent.591.com.tw/21293629",
      "package_num": 2,
      "days": 18,
      "status": "active",
      "owner": "未知",
      "featured": false,
      "topped": ""
    },
    {
      "link_id": "21237210",
      "title": "【優式】寬敞露臺景觀房/南勢角、景平雙捷運/可租補、報稅",
      "href": "https://rent.591.com.tw/21237210",
      "package_num": 2,
      "days": 18,
      "status": "active",
      "owner": "關宗宇",
      "featured": false,
      "topped": "超級置頂"
    },
    {
      "link_id": "21295197",
      "title": "【優式】徐匯中學站/尼加拉瓜公園/採光2房生活機能佳⭐小謙",
      "href": "https://rent.591.com.tw/21295197",
      "package_num": 2,
      "days": 19,
      "status": "active",
      "owner": "曾宇謙",
      "featured": false,
      "topped": ""
    },
    {
      "link_id": "21309572",
      "title": "🎉西門站｜可租補｜電梯二房｜便利商圈🍀阿宣🍀",
      "href": "https://rent.591.com.tw/21309572",
      "package_num": 2,
      "days": 19,
      "status": "active",
      "owner": "未知",
      "featured": false,
      "topped": "超級置頂"
    },
    {
      "link_id": "21293558",
      "title": "【優式】捷運三重站/全新陽光明亮3房/家俱可談",
      "href": "https://rent.591.com.tw/21293558",
      "package_num": 2,
      "days": 19,
      "status": "active",
      "owner": "關宗宇",
      "featured": false,
      "topped": "超級置頂"
    },
    {
      "link_id": "21249377",
      "title": "🎉行天宮站｜歡迎合租｜全新家具家電｜含水/網路🍀阿宣🍀",
      "href": "https://rent.591.com.tw/21249377",
      "package_num": 2,
      "days": 20,
      "status": "active",
      "owner": "林宣佑",
      "featured": false,
      "topped": "超級置頂"
    },
    {
      "link_id": "21297367",
      "title": "⭐️西門站｜可開伙｜系統收納丨代收包裹",
      "href": "https://rent.591.com.tw/21297367",
      "package_num": 2,
      "days": 20,
      "status": "active",
      "owner": "蕭靜芳",
      "featured": false,
      "topped": "超級置頂"
    },
    {
      "link_id": "21280388",
      "title": "✨西門站｜溫馨雅緻｜配備完善｜置物充裕🚀小鐘🚀",
      "href": "https://rent.591.com.tw/21280388",
      "package_num": 2,
      "days": 20,
      "status": "active",
      "owner": "鐘晟鈺",
      "featured": false,
      "topped": "超級置頂"
    },
    {
      "link_id": "21265798",
      "title": "🌈行天宮站｜北歐現代風｜新裝潢｜新家具☀️阿傳☀️",
      "href": "https://rent.591.com.tw/21265798",
      "package_num": 2,
      "days": 22,
      "status": "active",
      "owner": "詹張傳",
      "featured": false,
      "topped": ""
    },
    {
      "link_id": "21250969",
      "title": "A9站可租補，南勢靜巷電梯華廈，大陽台採光通風佳",
      "href": "https://rent.591.com.tw/21250969",
      "package_num": 2,
      "days": 22,
      "status": "active",
      "owner": "陳勁豪",
      "featured": false,
      "topped": "超級置頂"
    },
    {
      "link_id": "21269306",
      "title": "🌈女子公寓✨共生分租雅房❤️小碩❤️",
      "href": "https://rent.591.com.tw/21269306",
      "package_num": 2,
      "days": 23,
      "status": "active",
      "owner": "劉子碩",
      "featured": false,
      "topped": ""
    },
    {
      "link_id": "21268403",
      "title": "龍山寺丨日系丨採光佳丨可租補報稅丨進口家具🌟忠豪🌟",
      "href": "https://rent.591.com.tw/21268403",
      "package_num": 2,
      "days": 23,
      "status": "active",
      "owner": "張忠豪",
      "featured": false,
      "topped": ""
    },
    {
      "link_id": "21272032",
      "title": "台北橋站｜新裝潢｜免爬樓梯｜可租補入籍｜寵物可談",
      "href": "https://rent.591.com.tw/21272032",
      "package_num": 2,
      "days": 23,
      "status": "active",
      "owner": "林佳燕",
      "featured": false,
      "topped": "超級置頂"
    },
    {
      "link_id": "21283782",
      "title": "🚉板橋站｜舒適質感二房｜可租補報稅｜⭐卓威⭐",
      "href": "https://rent.591.com.tw/21283782",
      "package_num": 1,
      "days": 25,
      "status": "active",
      "owner": "李卓威",
      "featured": false,
      "topped": ""
    },
    {
      "link_id": "21281736",
      "title": "🔥三和國中丨可寵可開伙丨兩房有陽台",
      "href": "https://rent.591.com.tw/21281736",
      "package_num": 1,
      "days": 25,
      "status": "active",
      "owner": "蕭靜芳",
      "featured": false,
      "topped": "超級置頂"
    },
    {
      "link_id": "21281811",
      "title": "⭐️A三重站丨可寵可租補丨裝潢兩房可開伙",
      "href": "https://rent.591.com.tw/21281811",
      "package_num": 1,
      "days": 25,
      "status": "active",
      "owner": "蕭靜芳",
      "featured": false,
      "topped": "超級置頂"
    },
    {
      "link_id": "21281840",
      "title": "⭐️B三重站丨可寵可租補戶籍丨裝潢兩房可開伙",
      "href": "https://rent.591.com.tw/21281840",
      "package_num": 1,
      "days": 25,
      "status": "active",
      "owner": "蕭靜芳",
      "featured": false,
      "topped": "超級置頂"
    },
    {
      "link_id": "21282071",
      "title": "⭐️A三和國中丨可租補家具齊全丨採光佳",
      "href": "https://rent.591.com.tw/21282071",
      "package_num": 1,
      "days": 25,
      "status": "active",
      "owner": "蕭靜芳",
      "featured": false,
      "topped": "超級置頂"
    },
    {
      "link_id": "21282391",
      "title": "⭐️台北橋站丨可寵三房丨有陽台",
      "href": "https://rent.591.com.tw/21282391",
      "package_num": 1,
      "days": 25,
      "status": "active",
      "owner": "蕭靜芳",
      "featured": false,
      "topped": "超級置頂"
    },
    {
      "link_id": "21314812",
      "title": "⭐️三民高中丨2樓可租補丨台電天然瓦斯",
      "href": "https://rent.591.com.tw/21314812",
      "package_num": 1,
      "days": 25,
      "status": "active",
      "owner": "蕭靜芳",
      "featured": false,
      "topped": "超級置頂"
    },
    {
      "link_id": "21280130",
      "title": "✨板橋站｜可租補｜高質美宅｜高樓美景🚀小鐘🚀",
      "href": "https://rent.591.com.tw/21280130",
      "package_num": 2,
      "days": 25,
      "status": "active",
      "owner": "鐘晟鈺",
      "featured": false,
      "topped": ""
    },
    {
      "link_id": "21302849",
      "title": "【優式】三重站/景觀綠意木質設計2房/可租補",
      "href": "https://rent.591.com.tw/21302849",
      "package_num": 1,
      "days": 28,
      "status": "active",
      "owner": "吳惠慈",
      "featured": false,
      "topped": "超級置頂"
    },
    {
      "link_id": "21302405",
      "title": "6/10開放-信義安和可寵可租補大窗套房👍Howard👍",
      "href": "https://rent.591.com.tw/21302405",
      "package_num": 1,
      "days": 28,
      "status": "active",
      "owner": "張則泓",
      "featured": false,
      "topped": "超級置頂"
    },
    {
      "link_id": "21302879",
      "title": "三重丨全新丨可租補可寵丨專屬露台丨系統收納🌟忠豪🌟",
      "href": "https://rent.591.com.tw/21302879",
      "package_num": 1,
      "days": 28,
      "status": "active",
      "owner": "張忠豪",
      "featured": false,
      "topped": "超級置頂"
    },
    {
      "link_id": "21302984",
      "title": "三重都會公園丨全新未住丨採光佳丨家俱可談🌟忠豪🌟",
      "href": "https://rent.591.com.tw/21302984",
      "package_num": 1,
      "days": 28,
      "status": "active",
      "owner": "張忠豪",
      "featured": false,
      "topped": "超級置頂"
    },
    {
      "link_id": "21298296",
      "title": "🏠【象山站｜信義香榭精品宅｜可租補｜飯店式管理｜小方】",
      "href": "https://rent.591.com.tw/21298296",
      "package_num": 1,
      "days": 28,
      "status": "active",
      "owner": "方鼎文",
      "featured": false,
      "topped": ""
    },
    {
      "link_id": "21307520",
      "title": "【優式】三民捷運站/採光明亮大4房/生活機能強",
      "href": "https://rent.591.com.tw/21307520",
      "package_num": 1,
      "days": 29,
      "status": "active",
      "owner": "吳惠慈",
      "featured": false,
      "topped": "超級置頂"
    },
    {
      "link_id": "21301369",
      "title": "菜寮丨可寵物丨租金含網路第四台丨採光佳丨有陽台🌟忠豪🌟",
      "href": "https://rent.591.com.tw/21301369",
      "package_num": 1,
      "days": 29,
      "status": "active",
      "owner": "張忠豪",
      "featured": false,
      "topped": "超級置頂"
    },
    {
      "link_id": "21309969",
      "title": "蘆洲丨可租補丨可另租車位(含車充)丨前後陽台⭐️忠豪⭐️",
      "href": "https://rent.591.com.tw/21309969",
      "package_num": 1,
      "days": 29,
      "status": "active",
      "owner": "張忠豪",
      "featured": false,
      "topped": "超級置頂"
    },
    {
      "link_id": "21306634",
      "title": "三民高中丨低樓層丨新裝潢丨可租補丨台電帳單⭐️Wei⭐️",
      "href": "https://rent.591.com.tw/21306634",
      "package_num": 1,
      "days": 29,
      "status": "active",
      "owner": "蕭頤臻",
      "featured": false,
      "topped": "超級置頂"
    },
    {
      "link_id": "21314920",
      "title": "⭐️菜寮丨可寵丨含水網路第四台丨有陽台採光通風佳",
      "href": "https://rent.591.com.tw/21314920",
      "package_num": 1,
      "days": 30,
      "status": "active",
      "owner": "蕭靜芳",
      "featured": false,
      "topped": "超級置頂"
    }
  ],
  "expiring": [],
  "featured_list": [],
  "topped_list": [
    {
      "link_id": "21138327",
      "title": "【優式】南勢角站/靜巷內庭院透天3房/可養寵物",
      "href": "https://rent.591.com.tw/21138327",
      "package_num": 3,
      "days": 4,
      "status": "active",
      "owner": "關宗宇",
      "featured": false,
      "topped": "超級置頂"
    },
    {
      "link_id": "21299354",
      "title": "徐匯中學/屋齡輕採光大2房/生活機能佳🌟馬丁",
      "href": "https://rent.591.com.tw/21299354",
      "package_num": 3,
      "days": 4,
      "status": "active",
      "owner": "關宗宇",
      "featured": false,
      "topped": "超級置頂"
    },
    {
      "link_id": "21151001",
      "title": "🌿西門商圈｜電梯2房｜生活機能佳｜大台北生活圈｜小方🌿",
      "href": "https://rent.591.com.tw/21151001",
      "package_num": 3,
      "days": 5,
      "status": "active",
      "owner": "方鼎文",
      "featured": false,
      "topped": "超級置頂"
    },
    {
      "link_id": "21297242",
      "title": "C台北橋站丨含網路第四台丨獨立衛浴丨共用陽台",
      "href": "https://rent.591.com.tw/21297242",
      "package_num": 3,
      "days": 7,
      "status": "active",
      "owner": "蕭靜芳",
      "featured": false,
      "topped": "超級置頂"
    },
    {
      "link_id": "21292440",
      "title": "徐匯中學站｜高樓景觀2房｜空間舒適｜寵可談🌺Amber🌺",
      "href": "https://rent.591.com.tw/21292440",
      "package_num": 3,
      "days": 9,
      "status": "active",
      "owner": "林佳燕",
      "featured": false,
      "topped": "超級置頂"
    },
    {
      "link_id": "21209511",
      "title": "⭐景安站⭐捷運共構宅｜大空間好規劃｜包裹垃圾代收🌈卓威🌈",
      "href": "https://rent.591.com.tw/21209511",
      "package_num": 3,
      "days": 11,
      "status": "active",
      "owner": "未知",
      "featured": false,
      "topped": "超級置頂"
    },
    {
      "link_id": "21195203",
      "title": "菜寮丨可租補報稅丨可貓丨採光佳丨系統收納🌟忠豪🌟",
      "href": "https://rent.591.com.tw/21195203",
      "package_num": 3,
      "days": 12,
      "status": "active",
      "owner": "張忠豪",
      "featured": false,
      "topped": "超級置頂"
    },
    {
      "link_id": "21195341",
      "title": "三民高中丨專屬露台丨雙衛浴丨可另租車位⭐️忠豪⭐️",
      "href": "https://rent.591.com.tw/21195341",
      "package_num": 3,
      "days": 12,
      "status": "active",
      "owner": "張忠豪",
      "featured": false,
      "topped": "超級置頂"
    },
    {
      "link_id": "21238677",
      "title": "三和國中丨可租補報稅丨房間乾淨丨生活機能佳🌟忠豪🌟",
      "href": "https://rent.591.com.tw/21238677",
      "package_num": 3,
      "days": 12,
      "status": "active",
      "owner": "張忠豪",
      "featured": false,
      "topped": "超級置頂"
    },
    {
      "link_id": "21206400",
      "title": "【優式】忠孝復興站，家具齊全、可租補",
      "href": "https://rent.591.com.tw/21206400",
      "package_num": 2,
      "days": 14,
      "status": "active",
      "owner": "未知",
      "featured": false,
      "topped": "超級置頂"
    },
    {
      "link_id": "21211568",
      "title": "徐匯中學站/高樓採光景觀2房/生活機能佳⭐馬丁",
      "href": "https://rent.591.com.tw/21211568",
      "package_num": 2,
      "days": 14,
      "status": "active",
      "owner": "未知",
      "featured": false,
      "topped": "超級置頂"
    },
    {
      "link_id": "21253941",
      "title": "⭐️板橋站丨可租補報稅丨含管丨可租平面車位",
      "href": "https://rent.591.com.tw/21253941",
      "package_num": 2,
      "days": 14,
      "status": "active",
      "owner": "蕭靜芳",
      "featured": false,
      "topped": "超級置頂"
    },
    {
      "link_id": "21297466",
      "title": "⭐️H三和國中站丨女性丨有陽台洗衣機可使用",
      "href": "https://rent.591.com.tw/21297466",
      "package_num": 2,
      "days": 14,
      "status": "active",
      "owner": "蕭靜芳",
      "featured": false,
      "topped": "超級置頂"
    },
    {
      "link_id": "21221010",
      "title": "🎉板橋站｜可租補報稅｜質感系統設計｜景觀2房🍀阿宣🍀",
      "href": "https://rent.591.com.tw/21221010",
      "package_num": 2,
      "days": 15,
      "status": "active",
      "owner": "林宣佑",
      "featured": false,
      "topped": "超級置頂"
    },
    {
      "link_id": "21272695",
      "title": "三民高中丨可租補丨低樓層丨租金含水丨屋況乾淨🌟忠豪🌟",
      "href": "https://rent.591.com.tw/21272695",
      "package_num": 2,
      "days": 16,
      "status": "active",
      "owner": "張忠豪",
      "featured": false,
      "topped": "超級置頂"
    },
    {
      "link_id": "21224108",
      "title": "🎉西門站｜飯店管理｜乾淨舒適｜系統收納🍀阿宣",
      "href": "https://rent.591.com.tw/21224108",
      "package_num": 2,
      "days": 16,
      "status": "active",
      "owner": "未知",
      "featured": false,
      "topped": "超級置頂"
    },
    {
      "link_id": "21229539",
      "title": "南勢角站/靜巷內一樓大三房/生活機能佳",
      "href": "https://rent.591.com.tw/21229539",
      "package_num": 2,
      "days": 17,
      "status": "active",
      "owner": "關宗宇",
      "featured": false,
      "topped": "超級置頂"
    },
    {
      "link_id": "21279644",
      "title": "🎉板橋區｜質感電梯二房｜採光佳｜拎包入住🍀阿宣🍀",
      "href": "https://rent.591.com.tw/21279644",
      "package_num": 2,
      "days": 18,
      "status": "active",
      "owner": "未知",
      "featured": false,
      "topped": "超級置頂"
    },
    {
      "link_id": "21237210",
      "title": "【優式】寬敞露臺景觀房/南勢角、景平雙捷運/可租補、報稅",
      "href": "https://rent.591.com.tw/21237210",
      "package_num": 2,
      "days": 18,
      "status": "active",
      "owner": "關宗宇",
      "featured": false,
      "topped": "超級置頂"
    },
    {
      "link_id": "21309572",
      "title": "🎉西門站｜可租補｜電梯二房｜便利商圈🍀阿宣🍀",
      "href": "https://rent.591.com.tw/21309572",
      "package_num": 2,
      "days": 19,
      "status": "active",
      "owner": "未知",
      "featured": false,
      "topped": "超級置頂"
    },
    {
      "link_id": "21293558",
      "title": "【優式】捷運三重站/全新陽光明亮3房/家俱可談",
      "href": "https://rent.591.com.tw/21293558",
      "package_num": 2,
      "days": 19,
      "status": "active",
      "owner": "關宗宇",
      "featured": false,
      "topped": "超級置頂"
    },
    {
      "link_id": "21249377",
      "title": "🎉行天宮站｜歡迎合租｜全新家具家電｜含水/網路🍀阿宣🍀",
      "href": "https://rent.591.com.tw/21249377",
      "package_num": 2,
      "days": 20,
      "status": "active",
      "owner": "林宣佑",
      "featured": false,
      "topped": "超級置頂"
    },
    {
      "link_id": "21297367",
      "title": "⭐️西門站｜可開伙｜系統收納丨代收包裹",
      "href": "https://rent.591.com.tw/21297367",
      "package_num": 2,
      "days": 20,
      "status": "active",
      "owner": "蕭靜芳",
      "featured": false,
      "topped": "超級置頂"
    },
    {
      "link_id": "21280388",
      "title": "✨西門站｜溫馨雅緻｜配備完善｜置物充裕🚀小鐘🚀",
      "href": "https://rent.591.com.tw/21280388",
      "package_num": 2,
      "days": 20,
      "status": "active",
      "owner": "鐘晟鈺",
      "featured": false,
      "topped": "超級置頂"
    },
    {
      "link_id": "21250969",
      "title": "A9站可租補，南勢靜巷電梯華廈，大陽台採光通風佳",
      "href": "https://rent.591.com.tw/21250969",
      "package_num": 2,
      "days": 22,
      "status": "active",
      "owner": "陳勁豪",
      "featured": false,
      "topped": "超級置頂"
    },
    {
      "link_id": "21272032",
      "title": "台北橋站｜新裝潢｜免爬樓梯｜可租補入籍｜寵物可談",
      "href": "https://rent.591.com.tw/21272032",
      "package_num": 2,
      "days": 23,
      "status": "active",
      "owner": "林佳燕",
      "featured": false,
      "topped": "超級置頂"
    },
    {
      "link_id": "21281736",
      "title": "🔥三和國中丨可寵可開伙丨兩房有陽台",
      "href": "https://rent.591.com.tw/21281736",
      "package_num": 1,
      "days": 25,
      "status": "active",
      "owner": "蕭靜芳",
      "featured": false,
      "topped": "超級置頂"
    },
    {
      "link_id": "21281811",
      "title": "⭐️A三重站丨可寵可租補丨裝潢兩房可開伙",
      "href": "https://rent.591.com.tw/21281811",
      "package_num": 1,
      "days": 25,
      "status": "active",
      "owner": "蕭靜芳",
      "featured": false,
      "topped": "超級置頂"
    },
    {
      "link_id": "21281840",
      "title": "⭐️B三重站丨可寵可租補戶籍丨裝潢兩房可開伙",
      "href": "https://rent.591.com.tw/21281840",
      "package_num": 1,
      "days": 25,
      "status": "active",
      "owner": "蕭靜芳",
      "featured": false,
      "topped": "超級置頂"
    },
    {
      "link_id": "21282071",
      "title": "⭐️A三和國中丨可租補家具齊全丨採光佳",
      "href": "https://rent.591.com.tw/21282071",
      "package_num": 1,
      "days": 25,
      "status": "active",
      "owner": "蕭靜芳",
      "featured": false,
      "topped": "超級置頂"
    },
    {
      "link_id": "21282391",
      "title": "⭐️台北橋站丨可寵三房丨有陽台",
      "href": "https://rent.591.com.tw/21282391",
      "package_num": 1,
      "days": 25,
      "status": "active",
      "owner": "蕭靜芳",
      "featured": false,
      "topped": "超級置頂"
    },
    {
      "link_id": "21314812",
      "title": "⭐️三民高中丨2樓可租補丨台電天然瓦斯",
      "href": "https://rent.591.com.tw/21314812",
      "package_num": 1,
      "days": 25,
      "status": "active",
      "owner": "蕭靜芳",
      "featured": false,
      "topped": "超級置頂"
    },
    {
      "link_id": "21302849",
      "title": "【優式】三重站/景觀綠意木質設計2房/可租補",
      "href": "https://rent.591.com.tw/21302849",
      "package_num": 1,
      "days": 28,
      "status": "active",
      "owner": "吳惠慈",
      "featured": false,
      "topped": "超級置頂"
    },
    {
      "link_id": "21302405",
      "title": "6/10開放-信義安和可寵可租補大窗套房👍Howard👍",
      "href": "https://rent.591.com.tw/21302405",
      "package_num": 1,
      "days": 28,
      "status": "active",
      "owner": "張則泓",
      "featured": false,
      "topped": "超級置頂"
    },
    {
      "link_id": "21302879",
      "title": "三重丨全新丨可租補可寵丨專屬露台丨系統收納🌟忠豪🌟",
      "href": "https://rent.591.com.tw/21302879",
      "package_num": 1,
      "days": 28,
      "status": "active",
      "owner": "張忠豪",
      "featured": false,
      "topped": "超級置頂"
    },
    {
      "link_id": "21302984",
      "title": "三重都會公園丨全新未住丨採光佳丨家俱可談🌟忠豪🌟",
      "href": "https://rent.591.com.tw/21302984",
      "package_num": 1,
      "days": 28,
      "status": "active",
      "owner": "張忠豪",
      "featured": false,
      "topped": "超級置頂"
    },
    {
      "link_id": "21307520",
      "title": "【優式】三民捷運站/採光明亮大4房/生活機能強",
      "href": "https://rent.591.com.tw/21307520",
      "package_num": 1,
      "days": 29,
      "status": "active",
      "owner": "吳惠慈",
      "featured": false,
      "topped": "超級置頂"
    },
    {
      "link_id": "21301369",
      "title": "菜寮丨可寵物丨租金含網路第四台丨採光佳丨有陽台🌟忠豪🌟",
      "href": "https://rent.591.com.tw/21301369",
      "package_num": 1,
      "days": 29,
      "status": "active",
      "owner": "張忠豪",
      "featured": false,
      "topped": "超級置頂"
    },
    {
      "link_id": "21309969",
      "title": "蘆洲丨可租補丨可另租車位(含車充)丨前後陽台⭐️忠豪⭐️",
      "href": "https://rent.591.com.tw/21309969",
      "package_num": 1,
      "days": 29,
      "status": "active",
      "owner": "張忠豪",
      "featured": false,
      "topped": "超級置頂"
    },
    {
      "link_id": "21306634",
      "title": "三民高中丨低樓層丨新裝潢丨可租補丨台電帳單⭐️Wei⭐️",
      "href": "https://rent.591.com.tw/21306634",
      "package_num": 1,
      "days": 29,
      "status": "active",
      "owner": "蕭頤臻",
      "featured": false,
      "topped": "超級置頂"
    },
    {
      "link_id": "21314920",
      "title": "⭐️菜寮丨可寵丨含水網路第四台丨有陽台採光通風佳",
      "href": "https://rent.591.com.tw/21314920",
      "package_num": 1,
      "days": 30,
      "status": "active",
      "owner": "蕭靜芳",
      "featured": false,
      "topped": "超級置頂"
    }
  ],
  "owners": [
    {
      "name": "蕭靜芳",
      "active": 11,
      "expiring": 0,
      "featured": 0,
      "topped": 11
    },
    {
      "name": "張忠豪",
      "active": 11,
      "expiring": 0,
      "featured": 0,
      "topped": 8
    },
    {
      "name": "關宗宇",
      "active": 8,
      "expiring": 0,
      "featured": 0,
      "topped": 5
    },
    {
      "name": "未知",
      "active": 8,
      "expiring": 0,
      "featured": 0,
      "topped": 6
    },
    {
      "name": "林宣佑",
      "active": 3,
      "expiring": 0,
      "featured": 0,
      "topped": 2
    },
    {
      "name": "方鼎文",
      "active": 2,
      "expiring": 0,
      "featured": 0,
      "topped": 1
    },
    {
      "name": "劉子碩",
      "active": 2,
      "expiring": 0,
      "featured": 0,
      "topped": 0
    },
    {
      "name": "林佳燕",
      "active": 2,
      "expiring": 0,
      "featured": 0,
      "topped": 2
    },
    {
      "name": "詹張傳",
      "active": 2,
      "expiring": 0,
      "featured": 0,
      "topped": 0
    },
    {
      "name": "曾宇謙",
      "active": 2,
      "expiring": 0,
      "featured": 0,
      "topped": 0
    },
    {
      "name": "鐘晟鈺",
      "active": 2,
      "expiring": 0,
      "featured": 0,
      "topped": 1
    },
    {
      "name": "吳惠慈",
      "active": 2,
      "expiring": 0,
      "featured": 0,
      "topped": 2
    },
    {
      "name": "蕭眞儀",
      "active": 1,
      "expiring": 0,
      "featured": 0,
      "topped": 0
    },
    {
      "name": "陳勁豪",
      "active": 1,
      "expiring": 0,
      "featured": 0,
      "topped": 1
    },
    {
      "name": "李卓威",
      "active": 1,
      "expiring": 0,
      "featured": 0,
      "topped": 0
    },
    {
      "name": "張則泓",
      "active": 1,
      "expiring": 0,
      "featured": 0,
      "topped": 1
    },
    {
      "name": "蕭頤臻",
      "active": 1,
      "expiring": 0,
      "featured": 0,
      "topped": 1
    }
  ]
}